sage_sms/__init__.py
sage_sms/backends/__init__.py
sage_sms/backends/base.py
sage_sms/design/__init__.py
sage_sms/design/interfaces/__init__.py
sage_sms/design/interfaces/provider.py
sage_sms/factory.py
sage_sms/helper/__init__.py
sage_sms/helper/exceptions.py
sage_sms/helper/type.py
sage_sms/validators.py
python_sage_sms-0.1.1.dist-info/LICENSE
python_sage_sms-0.1.1.dist-info/METADATA
python_sage_sms-0.1.1.dist-info/WHEEL
python_sage_sms-0.1.1.dist-info/RECORD
