Metadata-Version: 2.1
Name: python-sage-sms
Version: 0.1.1
Summary: A Python package for sending SMS with different providers
License: MIT
Keywords: python,sms,integration
Author: Sepehr Akbarzadeh
Author-email: sepehr@sageteam.org
Requires-Python: >=3.9,<4.0
Classifier: License :: OSI Approved :: MIT License
Classifier: Operating System :: OS Independent
Classifier: Programming Language :: Python
Classifier: Programming Language :: Python :: 3
Classifier: Programming Language :: Python :: 3.9
Classifier: Programming Language :: Python :: 3.10
Classifier: Programming Language :: Python :: 3.11
Classifier: Programming Language :: Python :: 3.12
Classifier: Programming Language :: Python :: 3 :: Only
Classifier: Programming Language :: Python :: 3.8
Project-URL: Issues, https://github.com/sageteamorg/python-sage-sms/issues
Project-URL: Source Code, https://github.com/sageteamorg/python-sage-sms
